unset/__init__.py
unset-0.1.1.dist-info/METADATA
unset-0.1.1.dist-info/WHEEL
unset-0.1.1.dist-info/RECORD
