Metadata-Version: 2.4
Name: unset
Version: 0.1.1
Summary: A singleton sentinel value Unset for distinguishing unset from None in Python.
Author-email: Jimin <jimin@codetech.top>
Classifier: Intended Audience :: Developers
Classifier: Programming Language :: Python :: 3
Classifier: Programming Language :: Python :: 3 :: Only
Classifier: Programming Language :: Python :: 3.8
Classifier: Programming Language :: Python :: 3.9
Classifier: Programming Language :: Python :: 3.10
Classifier: Programming Language :: Python :: 3.11
Classifier: Programming Language :: Python :: 3.12
Requires-Python: >=3.8
Requires-Dist: pydantic-core<3,>=2
